typst_pyimage/__init__.py
typst_pyimage/__main__.py
typst_pyimage/_run.py
typst_pyimage/pyimage.typ
typst_pyimage-0.1.1.dist-info/METADATA
typst_pyimage-0.1.1.dist-info/WHEEL
typst_pyimage-0.1.1.dist-info/licenses/LICENSE
typst_pyimage-0.1.1.dist-info/RECORD
