Metadata-Version: 2.4
Name: typst_pyimage
Version: 0.1.1
Summary: Typst extension, adding support for generating figures using inline Python code
Project-URL: repository, https://github.com/patrick-kidger/typst_pyimage
Author-email: Patrick Kidger <contact@kidger.site>
License:                                  Apache License
License-File: LICENSE
Keywords: matplotlib,plotting,typst
Classifier: Development Status :: 3 - Alpha
Classifier: Intended Audience :: Developers
Classifier: Intended Audience :: Science/Research
Classifier: License :: OSI Approved :: Apache Software License
Classifier: Natural Language :: English
Classifier: Programming Language :: Python :: 3
Requires-Python: ~=3.8
Requires-Dist: matplotlib>=3.7.1
